philips_air_purifier/__init__.py
philips_air_purifier/comms.py
philips_air_purifier/status.py
philips_air_purifier-0.0.4.dist-info/LICENSE
philips_air_purifier-0.0.4.dist-info/METADATA
philips_air_purifier-0.0.4.dist-info/WHEEL
philips_air_purifier-0.0.4.dist-info/top_level.txt
philips_air_purifier-0.0.4.dist-info/RECORD
