Metadata-Version: 2.1
Name: philips-air-purifier
Version: 0.0.4
Summary: A Python API to monitor and control Philips air purifiers.
Home-page: https://github.com/urbas/philips-air-purifier
Author: Matej Urbas
Author-email: matej.urbas@gmail.com
License: UNKNOWN
Keywords: philips-air-purifier
Platform: UNKNOWN
Classifier: Intended Audience :: Developers
Classifier: License :: OSI Approved :: MIT License
Classifier: Natural Language :: English
Classifier: Programming Language :: Python :: 3.7
Requires-Dist: pycryptodome (>=3.0.0)
Requires-Dist: requests (>=2.0.0)
